bias_detector/BiasConfidence.py
bias_detector/BiasDetector.py
bias_detector/BiasMetric.py
bias_detector/BiasReport.py
bias_detector/GroupsResults.py
bias_detector/__init__.py
bias_detector/common.py
bias_detector/p_groups_lookup.py
bias_detector/bias_metrics/BiasMetricImpl.py
bias_detector/bias_metrics/BiasMetricInput.py
bias_detector/bias_metrics/BiasMetricOutput.py
bias_detector/bias_metrics/FprDiff.py
bias_detector/bias_metrics/PositivePredProbDiff.py
bias_detector/bias_metrics/TprDiff.py
bias_detector/bias_metrics/__init__.py
bias_detector/fuzzy_names_from_emails/FullName.py
bias_detector/fuzzy_names_from_emails/FuzzyEmailFullNameExtractor.py
bias_detector/fuzzy_names_from_emails/__init__.py
bias_detector/models/FirstNameModel.py
bias_detector/models/FirstNameZipcodeModel.py
bias_detector/models/FullNameModel.py
bias_detector/models/FullNameZipcodeModel.py
bias_detector/models/__init__.py
bias_detector/resources/p_first_name_given_race.csv
bias_detector/resources/p_gender_given_first_name.csv
bias_detector/resources/p_race_given_first_name.csv
tests/__init__.py
tests/common.py
tests/mocks_generator.py
tests/test_BiasDetector.py
tests/test_BiasReport.py
tests/test_FuzzyEmailFullNameExtractor.py
tests/test_mocks_generator.py
tests/test_p_groups_lookup.py
bias_detector-0.0.13.dist-info/LICENSE
bias_detector-0.0.13.dist-info/METADATA
bias_detector-0.0.13.dist-info/WHEEL
bias_detector-0.0.13.dist-info/top_level.txt
bias_detector-0.0.13.dist-info/RECORD
