Metadata-Version: 2.1
Name: bias-detector
Version: 0.0.13
Summary: Bias Detector is a python package for detecting bias in machine learning models
Home-page: https://github.com/intuit/bias-detector
Author: Elhanan Mishraky, Shir Lador, Aviv Benarie
Author-email: elhanan_mishraky@intuit.com, shir_lador@intuit.com, aviv_benarie@intuit.com
License: MIT
Classifier: Development Status :: 4 - Beta
Classifier: License :: OSI Approved :: MIT License
Classifier: Programming Language :: Python :: 3.6
Classifier: Topic :: Software Development :: Libraries
Classifier: Topic :: Software Development :: Libraries :: Python Modules
Classifier: Intended Audience :: Developers
Classifier: Operating System :: OS Independent
Requires-Python: >=3.6
License-File: LICENSE
Requires-Dist: numpy (>=1.19.4)
Requires-Dist: pandas (>=1.1.5)
Requires-Dist: scikit-learn (>=0.23.2)
Requires-Dist: matplotlib (>=3.3.3)
Requires-Dist: scipy (>=1.5.4)
Requires-Dist: surgeo (==1.0.2)
Requires-Dist: nltk (>=3.5)
Provides-Extra: test
Requires-Dist: pytest ; extra == 'test'
